{
    "USD_NOK": {
        "from_currency": "USD",
        "to_currency": "NOK",
        "exchange_rate": "11.059",
        "last_refreshed": "2024-11-21 20:20:03",
        "time_zone": "UTC"
    },
    "GBP_USD": {
        "from_currency": "GBP",
        "to_currency": "USD",
        "exchange_rate": "1.2596",
        "last_refreshed": "2024-11-21 20:20:01",
        "time_zone": "UTC"
    },
    "GBP_NOK": {
        "from_currency": "GBP",
        "to_currency": "NOK",
        "exchange_rate": "13.930",
        "last_refreshed": "2024-11-21 20:20:07",
        "time_zone": "UTC"
    },
    "DKK_NOK": {
        "from_currency": "DKK",
        "to_currency": "NOK",
        "exchange_rate": "1.5524",
        "last_refreshed": "2024-11-21 20:20:08",
        "time_zone": "UTC"
    },
    "SEK_NOK": {
        "from_currency": "SEK",
        "to_currency": "NOK",
        "exchange_rate": "0.9997",
        "last_refreshed": "2024-11-21 20:20:09",
        "time_zone": "UTC"
    },
    "EUR_NOK": {
        "from_currency": "EUR",
        "to_currency": "NOK",
        "exchange_rate": "11.589",
        "last_refreshed": "2024-11-21 20:20:06",
        "time_zone": "UTC"
    }
}